tuya_mcp_server/__init__.py
tuya_mcp_server/server.py
tuya_mcp_server-0.1.5.dist-info/METADATA
tuya_mcp_server-0.1.5.dist-info/WHEEL
tuya_mcp_server-0.1.5.dist-info/entry_points.txt
tuya_mcp_server-0.1.5.dist-info/licenses/LICENSE.md
tuya_mcp_server-0.1.5.dist-info/RECORD
