Metadata-Version: 2.4
Name: tuya-mcp-server
Version: 0.1.5
Summary: A MCP server for Tuya devices
Author-email: "@cabra.lat" <admin@cabra.lat>
License-File: LICENSE.md
Requires-Python: >=3.13
Requires-Dist: mcp[cli]>=1.2.1
Requires-Dist: numpy>=2.2.2
Requires-Dist: scipy>=1.15.1
Requires-Dist: tinytuya>=1.16.1
